evergreen_p_convolution/__init__.py
evergreen_p_convolution/_p_convolution.so
evergreen_p_convolution/p_convolution.py
evergreen_p_convolution-1.0.1.dist-info/LICENSE
evergreen_p_convolution-1.0.1.dist-info/METADATA
evergreen_p_convolution-1.0.1.dist-info/WHEEL
evergreen_p_convolution-1.0.1.dist-info/top_level.txt
evergreen_p_convolution-1.0.1.dist-info/RECORD
