Metadata-Version: 2.1
Name: evergreen-p-convolution
Version: 1.0.1
Summary: A python p_convolve package based on evergreenforest
Home-page: UNKNOWN
Author: Rice
Author-email: mrseanrice@gmail.com
License: UNKNOWN
Platform: UNKNOWN
Classifier: Programming Language :: Python :: 2.7
Classifier: License :: OSI Approved :: MIT License
